.gitignore
README.md
setup.py
agsi/__init__.py
agsi/demo_V2.ipynb
agsi/main.py
agsi/requirements.txt
agsi.egg-info/PKG-INFO
agsi.egg-info/SOURCES.txt
agsi.egg-info/dependency_links.txt
agsi.egg-info/requires.txt
agsi.egg-info/top_level.txt
agsi/__pycache__/__init__.cpython-38.pyc
agsi/data/FarmData.py
agsi/data/Indices.py
agsi/data/SatelliteData.py
agsi/data/__init__.py
agsi/data/band_info.py
agsi/data/utils.py