Metadata-Version: 1.0
Name: agsi
Version: 3.0
Summary: A package for agricultural sensing in India
Home-page: UNKNOWN
Author: UNKNOWN
Author-email: UNKNOWN
License: UNKNOWN
Platform: UNKNOWN
